ringfencer/entry_point.py
ringfencer/_version.py
ringfencer/__init__.py
ringfencer/__main__.py
Ringfencer-0.1.0.dist-info/DESCRIPTION.rst
Ringfencer-0.1.0.dist-info/METADATA
Ringfencer-0.1.0.dist-info/metadata.json
Ringfencer-0.1.0.dist-info/RECORD
Ringfencer-0.1.0.dist-info/top_level.txt
Ringfencer-0.1.0.dist-info/WHEEL
