Metadata-Version: 2.0
Name: Ringfencer
Version: 0.1.0
Summary: Determine which clients are located within a certain range of a specified point on the Earth's surface (so that you can invite them round for food and drink).
Home-page: https://github.com/martinpengellyphillips/ringfencer
Author: Martin Pengelly-Phillips
Author-email: martin@4degrees.ltd.uk
License: Apache License (2.0)
Keywords: location,gps,range,distance,longitude,latitude
Platform: UNKNOWN
